dat_test/__init__.py
dat_test/tn_nodrive.py
DAT_test-0.0.1.dist-info/LICENCE.txt
DAT_test-0.0.1.dist-info/METADATA
DAT_test-0.0.1.dist-info/WHEEL
DAT_test-0.0.1.dist-info/top_level.txt
DAT_test-0.0.1.dist-info/RECORD
