Metadata-Version: 2.1
Name: DAT-test
Version: 0.0.1
Summary: blablabla
Home-page: https://github.com/toto/titi
Author: auteur
Author-email: test@gmail.com
License: UNKNOWN
Platform: UNKNOWN
Classifier: Programming Language :: Python :: 3
Classifier: License :: OSI Approved :: MIT License
Classifier: Operating System :: OS Independent
Requires-Python: >=3.7
License-File: LICENCE.txt
